intrag_sdk/__init__.py
intrag_sdk/passivo/__init__.py
intrag_sdk/passivo/client.py
intrag_sdk/passivo/file_types.py
intrag_sdk/simpledbf/__init__.py
intrag_sdk-0.1.7.dist-info/METADATA
intrag_sdk-0.1.7.dist-info/WHEEL
intrag_sdk-0.1.7.dist-info/RECORD
