Metadata-Version: 2.3
Name: intrag-sdk
Version: 0.1.7
Summary: Add your description here
Project-URL: Repository, https://github.com/WilianZilv/intrag_sdk
Author-email: Wilian <wilianzilv@gmail.com>
Requires-Python: >=3.7.1
Requires-Dist: beautifulsoup4>=4.12.2
Requires-Dist: pandas>=1.3.5
Requires-Dist: requests>=1.0.0
